union_find.py
union_find-0.0.1.dist-info/DESCRIPTION.rst
union_find-0.0.1.dist-info/METADATA
union_find-0.0.1.dist-info/RECORD
union_find-0.0.1.dist-info/WHEEL
union_find-0.0.1.dist-info/metadata.json
union_find-0.0.1.dist-info/top_level.txt
