Metadata-Version: 2.0
Name: union-find
Version: 0.0.1
Summary: union-find data structure.
Home-page: http://github.com/minghu6/union-find
Author: UNKNOWN
Author-email: UNKNOWN
License: MIT-LICENSE
Platform: any
Classifier: Development Status :: 5 - Production/Stable
Classifier: Intended Audience :: Developers
Classifier: License :: OSI Approved :: MIT License
Classifier: Programming Language :: Python :: 2
Classifier: Programming Language :: Python :: 3
Classifier: Programming Language :: Python :: Implementation :: CPython
Classifier: Programming Language :: Python :: Implementation :: PyPy
